[
    {
        "id": 0,
        "genre": ["драма"],
        "age": 16,
        "backdrop_path": "/images/movies/the_green_mile.webp",
        "original_title": "The Green Mile",
        "title": "Зелёная миля",
        "vote_average": 9.2,
        "duration": "3 часа 8 минут",
        "release_date": "1999",
        "country": "США",
        "trailer": "/trailers/the_green_mile.mp4",
        "slug": "the_green_mile"     
    },
    {
        
        "id": 1,
        "genre": ["драма"],
        "age": 16,
        "backdrop_path": "/images/movies/the_shawshank_redemption.webp",
        "original_title": "The Shawshank Redemption",
        "title": "Побег из Шоушенка",
        "vote_average": 9.0,
        "duration": "2 часа 22 минуты",
        "release_date": "1994",
        "country": "США",
        "trailer": "",
        "slug": "the_shawshank_redemption"
    },
    {
        "id": 2,
        "genre": ["драма"],
        "age": 16,
        "backdrop_path": "/images/movies/forrest_gump.webp",
        "original_title": "Forrest Gump",
        "title": "Форрест Гамп",
        "vote_average": 8.9,
        "duration": "2 часа 22 минуты",
        "release_date": "1994",
        "country": "США",
        "trailer": "",
        "slug": "forrest_gump"
    },
    {
        "id": 3,
        "genre": ["фэнтези"],
        "age": 12,
        "backdrop_path": "/images/movies/the_lord_of_the_rings_the_return_of_the_king.webp",
        "original_title": "The Lord of the Rings: The Return of the King",
        "title": "Властелин колец: Возвращение короля",
        "vote_average": 8.9,
        "duration": "3 часа 21 минута",
        "release_date": "2003",
        "country": "Новая Зеландия",
        "trailer": "",
        "slug": "the_lord_of_the_rings_the_return_of_the_king"
    },
    {
        "id": 4,
        "genre": ["фэнтези"],
        "age": 12,
        "backdrop_path": "/images/movies/the_lord_of_the_rings_the_fellowship_of_the_ring.webp",
        "original_title": "The Lord of the Rings: The Fellowship of the Ring",
        "title": "Властелин колец: Братство Кольца",
        "vote_average": 8.8,
        "duration": "2 часа 58 минут",
        "release_date": "2001",
        "country": "Новая Зеландия",
        "trailer": "",
        "slug": "the_lord_of_the_rings_the_fellowship_of_the_ring"
    },
    {
        "id": 5,
        "genre": ["фэнтези"],
        "age": "12",
        "backdrop_path": "/images/movies/the_lord_of_the_rings_the_two_towers.webp",
        "original_title": "The Lord of the Rings: The Two Towers",
        "title": "Властелин колец: Две крепости",
        "vote_average": 8.8,
        "duration": "2 часа 59 минут",
        "release_date": "2002",
        "country": "Новая Зеландия",
        "trailer": "",
        "slug": "the_lord_of_the_rings_the_two_towers"
    },
    {
        "id": 6,
        "genre": ["фантастика"],
        "age": "16",
        "backdrop_path": "/images/movies/interstellar.webp",
        "original_title": "Interstellar",
        "title": "Интерстеллар",
        "vote_average": 8.8,
        "duration": "2 часа 49 минут",
        "release_date": "2014",
        "country": "США",
        "trailer": "",
        "slug": "interstellar"
    },
    {
        "id": 7,
        "genre": ["фантастика"],
        "age": "12",
        "backdrop_path": "/images/movies/back_to_the_future.webp",
        "original_title": "Back to the Future",
        "title": "Назад в будущее",
        "vote_average": 8.8,
        "duration": "1 час 56 минут",
        "release_date": "1985",
        "country": "США",
        "trailer": "",
        "slug": "back_to_the_future"
    },
    {
        "id": 8,
        "genre": ["фантастика"],
        "age": "16",
        "backdrop_path": "/images/movies/the_dark_knight.webp",
        "original_title": "The Dark Knight",
        "title": "Тёмный рыцарь",
        "vote_average": 8.7,
        "duration": "2 часа 32 минуты",
        "release_date": "2008",
        "country": "США",
        "trailer": "",
        "slug": "the_dark_knight"
    },
    {
        "id": 9,
        "genre": ["триллер"],
        "age": "18",
        "backdrop_path": "/images/movies/fight_club.webp",
        "original_title": "Fight Club",
        "title": "Бойцовский клуб",
        "vote_average": 8.7,
        "duration": "2 часа 19 минут",
        "release_date": "1999",
        "country": "США",
        "trailer": "",
        "slug": "fight_club"
    },
    {
        "id": 10,
        "genre": ["история"],
        "age": "16",
        "backdrop_path": "/images/movies/gladiator.webp",
        "original_title": "Gladiator",
        "title": "Гладиатор",
        "vote_average": 8.7,
        "duration": "2 часа 35 минут",
        "release_date": "2000",
        "country": "США",
        "trailer": "",
        "slug": "gladiator"
    },
    {
        "id": 11,
        "genre": ["фантастика"],
        "age": "12",
        "backdrop_path": "/images/movies/inception.webp",
        "original_title": "Inception",
        "title": "Начало",
        "vote_average": 8.6,
        "duration": "2 часа 28 минут",
        "release_date": "2010",
        "country": "США",
        "trailer": "",
        "slug": "inception"
    },
    {
        "id": 12,
        "genre": ["фэнтези"],
        "age": "12",
        "backdrop_path": "/images/movies/pirates_of_the_caribbean_the_curse_of_the_black_pearl.webp",
        "original_title": "Pirates of the Caribbean: The Curse of the Black Pearl",
        "title": "Пираты Карибского моря: Проклятие чёрной жемчужины",
        "vote_average": 8.6,
        "duration": "2 часа 23 минуты",
        "release_date": "2003",
        "country": "США",
        "trailer": "",
        "slug": "pirates_of_the_caribbean_the_curse_of_the_black_pearl"
    },
    {
        "id": 13,
        "genre": ["криминал"],
        "age": "12",
        "backdrop_path": "/images/movies/catch_me_if_you_can.webp",
        "original_title": "Catch Me If You Can",
        "title": "Поймай меня, если сможешь",
        "vote_average": 8.6,
        "duration": "2 часа 21 минута",
        "release_date": "2002",
        "country": "США",
        "trailer": "",
        "slug": "catch_me_if_you_can"
    },
    {
        "id": 14,
        "genre": ["фэнтези"],
        "age": "12",
        "backdrop_path": "/images/movies/harry_potter_and_the_sorcerers_stone.webp",
        "original_title": "Harry Potter and the Sorcerer's Stone",
        "title": "Гарри Поттер и филосовский камень",
        "vote_average": 8.5,
        "duration": "2 часа 32 минуты",
        "release_date": "2001",
        "country": "Великобритания",
        "trailer": "",
        "slug": "harry_potter_and_the_sorcerers_stone"
    },
    {
        "id": 15,
        "genre": ["мелодрама"],
        "age": "12",
        "backdrop_path": "/images/movies/titanic.webp",
        "original_title": "Titanic",
        "title": "Титаник",
        "vote_average": 8.5,
        "duration": "3 часа 14 минут",
        "release_date": "1997",
        "country": "США",
        "trailer": "",
        "slug": "titanic"
    },
    {
        "id": 16,
        "genre": ["фэнтези"],
        "age": "12",
        "backdrop_path": "/images/movies/harry_potter_and_the_prisoner_of_azkaban.webp",
        "original_title": "Harry Potter and the Prisoner of Azkaban",
        "title": "Гарри Поттер и узник Азкабана",
        "vote_average": 8.5,
        "duration": "2 часа 22 минуты",
        "release_date": "2004",
        "country": "Великобритания",
        "trailer": "",
        "slug": "harry_potter_and_the_prisoner_of_azkaban"
    },
    {
        "id": 17,
        "genre": ["боевик"],
        "age": "16",
        "backdrop_path": "/images/movies/leon.webp",
        "original_title": "Leon",
        "title": "Леон",
        "vote_average": 8.5,
        "duration": "2 часа 13 минут",
        "release_date": "1994",
        "country": "Франция",
        "trailer": "",
        "slug": "leon"
    },
    {
        "id": 18,
        "genre": ["вестерн"],
        "age": "18",
        "backdrop_path": "/images/movies/django_unchained.webp",
        "original_title": "Django Unchained",
        "title": "Джанго освобождённый",
        "vote_average": 8.5,
        "duration": "2 часа 45 минут",
        "release_date": "2012",
        "country": "США",
        "trailer": "",
        "slug": "django_unchained"
    },
    {
        "id": 19,
        "genre": ["фантастика"],
        "age": "12",
        "backdrop_path": "/images/movies/back_to_the_future_part_II.webp",
        "original_title": "Back to the Future Part II",
        "title": "Назад в будущее 2",
        "vote_average": 8.5,
        "duration": "1 час 48 минут",
        "release_date": "1989",
        "country": "США",
        "trailer": "",
        "slug": "back_to_the_future_part_II"
    },
    {
        "id": 20,
        "genre": ["фантастика"],
        "age": "16",
        "backdrop_path": "/images/movies/the_matrix.webp",
        "original_title": "the Matrix",
        "title": "Матрица",
        "vote_average": 8.5,
        "duration": "2 часа 16 минут",
        "release_date": "1999",
        "country": "США",
        "trailer": "",
        "slug": "the_matrix"
    },
    {
        "id": 21,
        "genre": ["фэнтези"],
        "age": "12",
        "backdrop_path": "/images/movies/pirates_of_the_caribbean_dead_mans_chest.webp",
        "original_title": "Pirates of the Caribbean: Dead Man's Chest",
        "title": "Пираты Карибского моря: Сундук мертвеца",
        "vote_average": 8.5,
        "duration": "2 часа 31 минута",
        "release_date": "2006",
        "country": "США",
        "trailer": "",
        "slug": "pirates_of_the_caribbean_dead_mans_chest"
    }
]